fitbit_data_pipeline/__init__.py
fitbit_data_pipeline/auth/__init__.py
fitbit_data_pipeline/auth/app_server.py
fitbit_data_pipeline/Classes/__init__.py
fitbit_data_pipeline/Classes/DataCollector.py
fitbit_data_pipeline/Classes/Participant.py
fitbit_data_pipeline/Classes/PManager.py
fitbit_data_pipeline/cli.py
fitbit_data_pipeline/runner.py
fitbit_data_pipeline/Utility.py
fitbit_data_pipeline-1.0.3.dist-info/entry_points.txt
fitbit_data_pipeline-1.0.3.dist-info/LICENSE
fitbit_data_pipeline-1.0.3.dist-info/METADATA
fitbit_data_pipeline-1.0.3.dist-info/WHEEL
fitbit_data_pipeline-1.0.3.dist-info/RECORD
